bothpy_ctp/__init__.py
bothpy_ctp/api/__init__.py
bothpy_ctp/api/ctp_constant.py
bothpy_ctp/api/libthostmduserapi_se.so
bothpy_ctp/api/libthosttraderapi_se.so
bothpy_ctp/api/thostmduserapi_se.dll
bothpy_ctp/api/thosttraderapi_se.dll
bothpy_ctp/api/vnctpmd.cp310-win_amd64.pyd
bothpy_ctp/api/vnctptd.cp310-win_amd64.pyd
bothpy_ctp/api/generator/ctp_constant.py
bothpy_ctp/api/generator/ctp_md_header_define.h
bothpy_ctp/api/generator/ctp_md_header_function.h
bothpy_ctp/api/generator/ctp_md_header_on.h
bothpy_ctp/api/generator/ctp_md_header_process.h
bothpy_ctp/api/generator/ctp_md_source_function.cpp
bothpy_ctp/api/generator/ctp_md_source_module.cpp
bothpy_ctp/api/generator/ctp_md_source_on.cpp
bothpy_ctp/api/generator/ctp_md_source_process.cpp
bothpy_ctp/api/generator/ctp_md_source_switch.cpp
bothpy_ctp/api/generator/ctp_md_source_task.cpp
bothpy_ctp/api/generator/ctp_struct.py
bothpy_ctp/api/generator/ctp_td_header_define.h
bothpy_ctp/api/generator/ctp_td_header_function.h
bothpy_ctp/api/generator/ctp_td_header_on.h
bothpy_ctp/api/generator/ctp_td_header_process.h
bothpy_ctp/api/generator/ctp_td_source_function.cpp
bothpy_ctp/api/generator/ctp_td_source_module.cpp
bothpy_ctp/api/generator/ctp_td_source_on.cpp
bothpy_ctp/api/generator/ctp_td_source_process.cpp
bothpy_ctp/api/generator/ctp_td_source_switch.cpp
bothpy_ctp/api/generator/ctp_td_source_task.cpp
bothpy_ctp/api/generator/ctp_typedef.py
bothpy_ctp/api/generator/generate_api_functions.py
bothpy_ctp/api/generator/generate_data_type.py
bothpy_ctp/api/generator/generate_struct.py
bothpy_ctp/api/include/ctp/ThostFtdcMdApi.h
bothpy_ctp/api/include/ctp/ThostFtdcTraderApi.h
bothpy_ctp/api/include/ctp/ThostFtdcUserApiDataType.h
bothpy_ctp/api/include/ctp/ThostFtdcUserApiStruct.h
bothpy_ctp/api/include/mac/ctp/ThostFtdcMdApi.h
bothpy_ctp/api/include/mac/ctp/ThostFtdcTraderApi.h
bothpy_ctp/api/include/mac/ctp/ThostFtdcUserApiDataType.h
bothpy_ctp/api/include/mac/ctp/ThostFtdcUserApiStruct.h
bothpy_ctp-6.6.7.5.dist-info/LICENSE
bothpy_ctp-6.6.7.5.dist-info/METADATA
bothpy_ctp-6.6.7.5.dist-info/WHEEL
bothpy_ctp-6.6.7.5.dist-info/top_level.txt
bothpy_ctp-6.6.7.5.dist-info/RECORD
